cso_classifier/__init__.py
cso_classifier/classifier.py
cso_classifier/config.ini
cso_classifier/config.py
cso_classifier/misc.py
cso_classifier/model.py
cso_classifier/ontology.py
cso_classifier/paper.py
cso_classifier/postprocmodule.py
cso_classifier/result.py
cso_classifier/semanticmodule.py
cso_classifier/syntacticmodule.py
cso_classifier/test.py
cso_classifier/version.py
cso_classifier/assets/README.md
cso_classifier-3.1.dist-info/LICENSE
cso_classifier-3.1.dist-info/METADATA
cso_classifier-3.1.dist-info/WHEEL
cso_classifier-3.1.dist-info/top_level.txt
cso_classifier-3.1.dist-info/RECORD
