Metadata-Version: 2.1
Name: cso-classifier
Version: 3.1
Summary: A light-weight Python app for classifying scientific documents with the topics from the Computer Science Ontology (https://cso.kmi.open.ac.uk/home).
Home-page: https://github.com/angelosalatino/cso-classifier
Author: Angelo Salatino
Author-email: angelo.salatino@open.ac.uk
Classifier: Programming Language :: Python :: 3
Classifier: License :: OSI Approved :: Apache Software License
Classifier: Operating System :: OS Independent
Requires-Python: >=3.6.0
License-File: LICENSE
Requires-Dist: gensim (==3.8.3)
Requires-Dist: click (==7.1.2)
Requires-Dist: hurry.filesize (==0.9)
Requires-Dist: kneed (==0.3.1)
Requires-Dist: nltk (==3.6.2)
Requires-Dist: rapidfuzz (==2.11.1)
Requires-Dist: numpy (>=1.19.5)
Requires-Dist: requests (==2.25.1)
Requires-Dist: spacy (==3.0.5)
Requires-Dist: strsimpy (==0.2.0)
Requires-Dist: update-checker (==0.18.0)
Requires-Dist: python-igraph (==0.9.1) ; python_version < "3.7"
Requires-Dist: igraph (==0.10.4) ; python_version >= "3.7"
